LICENSE
MANIFEST.in
README.md
setup.py
exposor/__init__.py
exposor/exposor.py
exposor/data/ISO-3166-countries.json
exposor/data/syntax_unifier.yaml
exposor/feeds/__init__.py
exposor/feeds/query_builder.py
exposor/feeds/censys/__init__.py
exposor/feeds/censys/censys_feed.py
exposor/feeds/fofa/__init__.py
exposor/feeds/fofa/fofa_feed.py
exposor/feeds/shodan/__init__.py
exposor/feeds/shodan/shodan_feed.py
exposor/feeds/zoomeye/__init__.py
exposor/feeds/zoomeye/zoomeye_feed.py
exposor/intels/checksum.json
exposor/intels/technology_intels/01generator/pireospay/01generator_pireospay.yaml
exposor/intels/technology_intels/10web/photo_gallery/10web_photo_gallery.yaml
exposor/intels/technology_intels/2code/wpqa_builder/2code_wpqa_builder.yaml
exposor/intels/technology_intels/3cx/3cx/3cx_3cx.yaml
exposor/intels/technology_intels/4d/4d/4d_4d.yaml
exposor/intels/technology_intels/74cms/74cms/74cms_74cms.yaml
exposor/intels/technology_intels/a360inc/caseaware/a360inc_caseaware.yaml
exposor/intels/technology_intels/abb/aspect-ent-256/abb_aspect-ent-256.yaml
exposor/intels/technology_intels/abhinavsingh/wordpress_toolbar/abhinavsingh_wordpress_toolbar.yaml
exposor/intels/technology_intels/accellion/kiteworks/accellion_kiteworks.yaml
exposor/intels/technology_intels/acme/mini-httpd/acme_mini-httpd.yaml
exposor/intels/technology_intels/acquia/mautic/acquia_mautic.yaml
exposor/intels/technology_intels/activecollab/activecollab/activecollab_activecollab.yaml
exposor/intels/technology_intels/activehelper/activehelper_livehelp_live_chat/activehelper_activehelper_livehelp_live_chat.yaml
exposor/intels/technology_intels/acunetix/web_vulnerability_scanner/acunetix_web_vulnerability_scanner.yaml
exposor/intels/technology_intels/adguard/adguard/adguard_adguard.yaml
exposor/intels/technology_intels/admin-font-editor_project/admin-font-editor/admin-font-editor_project_admin-font-editor.yaml
exposor/intels/technology_intels/adobe/acs_aem_commons/adobe_acs_aem_commons.yaml
