Metadata-Version: 2.1
Name: exposor
Version: 1.0.0
Summary: Exposor - Unified query system for search engines
Home-page: https://github.com/abuyv/exposor
Author: Abdulla Abdullayev
Author-email: abu@abuyv.com
License: UNKNOWN
Platform: UNKNOWN
Classifier: Programming Language :: Python :: 3
Classifier: License :: OSI Approved :: MIT License
Classifier: Operating System :: OS Independent
Classifier: Topic :: Security
Requires-Python: >=3.8
